llama_index/embeddings/bedrock/__init__.py
llama_index/embeddings/bedrock/base.py
llama_index_embeddings_bedrock-0.7.3.dist-info/METADATA
llama_index_embeddings_bedrock-0.7.3.dist-info/WHEEL
llama_index_embeddings_bedrock-0.7.3.dist-info/licenses/LICENSE
llama_index_embeddings_bedrock-0.7.3.dist-info/RECORD
