Metadata-Version: 2.4
Name: llama-index-embeddings-bedrock
Version: 0.7.3
Summary: llama-index embeddings bedrock integration
Author-email: Your Name <you@example.com>
License-Expression: MIT
License-File: LICENSE
Requires-Python: <4.0,>=3.9
Requires-Dist: aioboto3<16,>=13.1.1
Requires-Dist: boto3<2,>=1.34.23
Requires-Dist: llama-index-core<0.15,>=0.13.0
